zcls2/__init__.py
zcls2/config/__init__.py
zcls2/config/key_word.py
zcls2/config/configs/__init__.py
zcls2/config/configs/custom_config.py
zcls2/config/configs/dataloader.py
zcls2/config/configs/dataset.py
zcls2/config/configs/defaults.py
zcls2/config/configs/lr_scheduler.py
zcls2/config/configs/model.py
zcls2/config/configs/optimizer.py
zcls2/config/configs/transform.py
zcls2/data/__init__.py
zcls2/data/build.py
zcls2/data/dataloader/__init__.py
zcls2/data/dataloader/build.py
zcls2/data/dataloader/collate.py
zcls2/data/dataset/__init__.py
zcls2/data/dataset/build.py
zcls2/data/dataset/cccf.py
zcls2/data/dataset/cifar.py
zcls2/data/dataset/general_dataset.py
zcls2/data/dataset/general_dataset_v2.py
zcls2/data/dataset/mix_dataset.py
zcls2/data/dataset/mp_dataset.py
zcls2/data/sampler/__init__.py
zcls2/data/sampler/build.py
zcls2/data/sampler/distributed_sampler.py
zcls2/data/transform/__init__.py
zcls2/data/transform/build.py
zcls2/data/transform/resize.py
zcls2/data/transform/square_pad.py
zcls2/engine/__init__.py
zcls2/engine/infer.py
zcls2/engine/trainer.py
zcls2/model/__init__.py
zcls2/model/criterion/__init__.py
zcls2/model/criterion/build.py
zcls2/model/criterion/cross_entropy_loss.py
zcls2/model/criterion/large_margin_softmax_loss.py
zcls2/model/criterion/soft_target_cross_entropy_loss.py
zcls2/model/model/__init__.py
zcls2/model/model/build.py
zcls2/model/model/efficientnet.py
zcls2/model/model/efficientnet_lite.py
zcls2/model/model/ghostnet.py
zcls2/model/model/mobilenet.py
zcls2/model/model/resnet.py
zcls2/model/model/util.py
zcls2/model/model/effnet_lite/__init__.py
zcls2/model/model/effnet_lite/efficientnet_lite.py
zcls2/model/model/effnet_lite/train.py
zcls2/model/model/effnet_lite/utils/__init__.py
zcls2/model/model/effnet_lite/utils/flops_counter.py
zcls2/model/model/effnet_lite/utils/train_utils.py
zcls2/optim/__init__.py
zcls2/optim/lr_scheduler/__init__.py
zcls2/optim/lr_scheduler/build.py
zcls2/optim/lr_scheduler/cosine_annealing_lr.py
zcls2-0.5.3.dist-info/LICENSE
zcls2-0.5.3.dist-info/METADATA
zcls2-0.5.3.dist-info/WHEEL
zcls2-0.5.3.dist-info/top_level.txt
zcls2-0.5.3.dist-info/RECORD
