Metadata-Version: 2.1
Name: zcls2
Version: 0.5.3
Summary: More Faster Object Classification Training Framework
Home-page: https://github.com/ZJCV/ZCls2
Author: zj
Author-email: wy163zhuj@163.com
License: UNKNOWN
Platform: UNKNOWN
Classifier: Programming Language :: Python :: 3
Classifier: Operating System :: OS Independent
Classifier: License :: OSI Approved :: Apache Software License
Requires-Python: >=3.8
License-File: LICENSE
Requires-Dist: Pillow (>=9.0.0)
Requires-Dist: numpy (>=1.22.3)
Requires-Dist: opencv-contrib-python (>=4.5.5.64)
Requires-Dist: tabulate (>=0.8.9)
Requires-Dist: timm (>=0.4.9)
Requires-Dist: torch (>=1.12.0)
Requires-Dist: torchvision (>=0.13.0)
Requires-Dist: yacs (>=0.1.8)
